odoo/addons/ssi_service_project/README.rst
odoo/addons/ssi_service_project/__init__.py
odoo/addons/ssi_service_project/__manifest__.py
odoo/addons/ssi_service_project/migrations/14.0.2.0.0/pre-migration.py
odoo/addons/ssi_service_project/models/__init__.py
odoo/addons/ssi_service_project/models/service_contract.py
odoo/addons/ssi_service_project/models/service_type.py
odoo/addons/ssi_service_project/static/description/icon.png
odoo/addons/ssi_service_project/views/service_contract_views.xml
odoo/addons/ssi_service_project/views/service_type_views.xml
odoo14_addon_ssi_service_project-14.0.2.0.3.dev1.dist-info/METADATA
odoo14_addon_ssi_service_project-14.0.2.0.3.dev1.dist-info/WHEEL
odoo14_addon_ssi_service_project-14.0.2.0.3.dev1.dist-info/top_level.txt
odoo14_addon_ssi_service_project-14.0.2.0.3.dev1.dist-info/RECORD
